odoo/addons/delivery_package_number/README.rst
odoo/addons/delivery_package_number/__init__.py
odoo/addons/delivery_package_number/__manifest__.py
odoo/addons/delivery_package_number/i18n/delivery_package_number.pot
odoo/addons/delivery_package_number/i18n/es.po
odoo/addons/delivery_package_number/i18n/sl.po
odoo/addons/delivery_package_number/models/__init__.py
odoo/addons/delivery_package_number/models/stock_picking.py
odoo/addons/delivery_package_number/readme/CONTRIBUTORS.rst
odoo/addons/delivery_package_number/readme/DESCRIPTION.rst
odoo/addons/delivery_package_number/readme/USAGE.rst
odoo/addons/delivery_package_number/static/description/icon.png
odoo/addons/delivery_package_number/static/description/index.html
odoo/addons/delivery_package_number/tests/__init__.py
odoo/addons/delivery_package_number/tests/test_delivery_package_number.py
odoo/addons/delivery_package_number/views/stock_picking_views.xml
odoo/addons/delivery_package_number/wizard/__init__.py
odoo/addons/delivery_package_number/wizard/stock_immediate_transfer_views.xml
odoo/addons/delivery_package_number/wizard/stock_inmediate_transfer.py
odoo13_addon_delivery_package_number-13.0.1.1.0.dist-info/METADATA
odoo13_addon_delivery_package_number-13.0.1.1.0.dist-info/WHEEL
odoo13_addon_delivery_package_number-13.0.1.1.0.dist-info/top_level.txt
odoo13_addon_delivery_package_number-13.0.1.1.0.dist-info/RECORD
